README.txt
setup.py
RandomDataLoader/DataLoader.py
RandomDataLoader/__main__.py
bin/RandomDataLoader.py
randomdataloader.egg-info/PKG-INFO
randomdataloader.egg-info/SOURCES.txt
randomdataloader.egg-info/dependency_links.txt
randomdataloader.egg-info/requires.txt
randomdataloader.egg-info/top_level.txt